covertreec.cpython-38-x86_64-linux-gnu.so
gldac.cpython-38-x86_64-linux-gnu.so
gmmc.cpython-38-x86_64-linux-gnu.so
hdpc.cpython-38-x86_64-linux-gnu.so
kmeansc.cpython-38-x86_64-linux-gnu.so
ldac.cpython-38-x86_64-linux-gnu.so
utilsc.cpython-38-x86_64-linux-gnu.so
fastlvm/__init__.py
fastlvm/covertree.py
fastlvm/covertree_classifier.py
fastlvm/covertree_regressor.py
fastlvm/dlda.py
fastlvm/glda.py
fastlvm/gmm.py
fastlvm/hdp.py
fastlvm/kmeans.py
fastlvm/lda.py
fastlvm/utils.py
fastlvm-3.1.1.dist-info/LICENSE
fastlvm-3.1.1.dist-info/METADATA
fastlvm-3.1.1.dist-info/WHEEL
fastlvm-3.1.1.dist-info/entry_points.txt
fastlvm-3.1.1.dist-info/top_level.txt
fastlvm-3.1.1.dist-info/RECORD
