Metadata-Version: 2.1
Name: fastlvm
Version: 3.1.1
Summary: fastlvm -- fast search, clustering, and mixture modelling
Author: CMU
Author-email: awillia2@andrew.cmu.edu
License: MIT
Keywords: d3m_primitive
Platform: UNKNOWN
License-File: LICENSE
Requires-Dist: numpy (>=1.13.1)
Requires-Dist: scipy (>=0.17)
Requires-Dist: scikit-learn (>=0.18.1)
Requires-Dist: gensim
